odoo/addons/ssi_general_audit_worksheet_control_risk/README.rst
odoo/addons/ssi_general_audit_worksheet_control_risk/__init__.py
odoo/addons/ssi_general_audit_worksheet_control_risk/__manifest__.py
odoo/addons/ssi_general_audit_worksheet_control_risk/menu.xml
odoo/addons/ssi_general_audit_worksheet_control_risk/data/general_audit_worksheet_type_data.xml
odoo/addons/ssi_general_audit_worksheet_control_risk/data/approval_template/general_audit_ws_ba9b2f0.xml
odoo/addons/ssi_general_audit_worksheet_control_risk/data/approval_template/general_audit_ws_d3d2719.xml
odoo/addons/ssi_general_audit_worksheet_control_risk/data/approval_template/general_audit_ws_eabdaad.xml
odoo/addons/ssi_general_audit_worksheet_control_risk/data/approval_template/general_audit_ws_f63f569.xml
odoo/addons/ssi_general_audit_worksheet_control_risk/data/ir_sequence/general_audit_ws_ba9b2f0.xml
odoo/addons/ssi_general_audit_worksheet_control_risk/data/ir_sequence/general_audit_ws_d3d2719.xml
odoo/addons/ssi_general_audit_worksheet_control_risk/data/ir_sequence/general_audit_ws_eabdaad.xml
odoo/addons/ssi_general_audit_worksheet_control_risk/data/ir_sequence/general_audit_ws_f63f569.xml
odoo/addons/ssi_general_audit_worksheet_control_risk/data/policy_template/general_audit_ws_ba9b2f0.xml
odoo/addons/ssi_general_audit_worksheet_control_risk/data/policy_template/general_audit_ws_d3d2719.xml
odoo/addons/ssi_general_audit_worksheet_control_risk/data/policy_template/general_audit_ws_eabdaad.xml
odoo/addons/ssi_general_audit_worksheet_control_risk/data/policy_template/general_audit_ws_f63f569.xml
odoo/addons/ssi_general_audit_worksheet_control_risk/data/sequence_template/general_audit_ws_ba9b2f0.xml
odoo/addons/ssi_general_audit_worksheet_control_risk/data/sequence_template/general_audit_ws_d3d2719.xml
odoo/addons/ssi_general_audit_worksheet_control_risk/data/sequence_template/general_audit_ws_eabdaad.xml
odoo14_addon_ssi_general_audit_worksheet_control_risk-14.0.2.2.0.dist-info/METADATA
odoo14_addon_ssi_general_audit_worksheet_control_risk-14.0.2.2.0.dist-info/WHEEL
odoo14_addon_ssi_general_audit_worksheet_control_risk-14.0.2.2.0.dist-info/top_level.txt
odoo14_addon_ssi_general_audit_worksheet_control_risk-14.0.2.2.0.dist-info/RECORD
